typedown/__init__.py
typedown/main.py
typedown/commands/__init__.py
typedown/commands/check.py
typedown/commands/lint.py
typedown/commands/lsp.py
typedown/commands/query.py
typedown/commands/run.py
typedown/commands/test.py
typedown/commands/validate.py
typedown/core/__init__.py
typedown/core/compiler.py
typedown/core/graph.py
typedown/core/spec_runtime.py
typedown/core/analysis/__init__.py
typedown/core/analysis/compiler_context.py
typedown/core/analysis/graph.py
typedown/core/analysis/linker.py
typedown/core/analysis/query.py
typedown/core/analysis/scanner.py
typedown/core/analysis/script_runner.py
typedown/core/analysis/source_provider.py
typedown/core/analysis/spec_executor.py
typedown/core/analysis/validator.py
typedown/core/ast/__init__.py
typedown/core/ast/base.py
typedown/core/ast/blocks.py
typedown/core/ast/document.py
typedown/core/base/__init__.py
typedown/core/base/compiler_context.py
typedown/core/base/config.py
typedown/core/base/errors.py
typedown/core/base/identifiers.py
typedown/core/base/resolver.py
typedown/core/base/symbol_table.py
typedown/core/base/types.py
typedown/core/base/utils.py
typedown/core/parser/__init__.py
typedown/core/parser/desugar.py
typedown/core/parser/typedown_parser.py
typedown/core/parser/utils.py
typedown/core/runtime/__init__.py
typedown/core/runtime/oracle.py
typedown/server/__init__.py
typedown/server/application.py
typedown/server/features/__init__.py
typedown/server/features/code_lens.py
typedown/server/features/completion.py
typedown/server/features/hover.py
typedown/server/features/lifecycle.py
typedown/server/features/navigation.py
typedown/server/features/rename.py
typedown/server/features/semantic_tokens.py
typedown/server/managers/__init__.py
typedown/server/managers/diagnostics.py
typedown/server/managers/watcher.py
typedown-0.2.17.dist-info/METADATA
typedown-0.2.17.dist-info/WHEEL
typedown-0.2.17.dist-info/entry_points.txt
typedown-0.2.17.dist-info/licenses/LICENSE
typedown-0.2.17.dist-info/RECORD
