Metadata-Version: 2.4
Name: typedown
Version: 0.2.17
Summary: Progressive Formalization for Markdown using Pydantic and Pytest
Project-URL: Homepage, https://typedown.io
Project-URL: Repository, https://github.com/IndenScale/Typedown
Project-URL: Documentation, https://typedown.io/docs
License-Expression: MIT
License-File: LICENSE
Keywords: data-entry,documentation,formalization,markdown,pydantic,spec
Classifier: Development Status :: 3 - Alpha
Classifier: Intended Audience :: Developers
Classifier: License :: OSI Approved :: MIT License
Classifier: Programming Language :: Python :: 3
Classifier: Programming Language :: Python :: 3.12
Classifier: Topic :: Documentation
Classifier: Topic :: Software Development :: Libraries :: Python Modules
Requires-Python: >=3.12
Requires-Dist: markdown-it-py>=3.0.0
Requires-Dist: mistune>=3.1.4
Requires-Dist: pydantic>=2.0.0
Requires-Dist: pytest>=7.0.0
Requires-Dist: python-frontmatter>=1.0.0
Requires-Dist: pyyaml>=6.0.0
Requires-Dist: rich>=13.0.0
Requires-Dist: tomli>=2.3.0
Requires-Dist: typer>=0.9.0
Provides-Extra: server
Requires-Dist: pygls>=1.0.0; extra == 'server'
Requires-Dist: watchdog>=3.0.0; extra == 'server'
Requires-Dist: websockets>=10.0; extra == 'server'
Provides-Extra: sql
Requires-Dist: duckdb>=0.9.0; extra == 'sql'
